brokerage/__init__.py
brokerage/brokerage.py
brokerage/make_simulator.py
brokerage/minimal_connect.py
brokerage-0.0.8.dist-info/LICENSE
brokerage-0.0.8.dist-info/METADATA
brokerage-0.0.8.dist-info/WHEEL
brokerage-0.0.8.dist-info/top_level.txt
brokerage-0.0.8.dist-info/RECORD
