Metadata-Version: 2.1
Name: brokerage
Version: 0.0.8
Summary: Simulate data feed from broker
Home-page: https://github.com/yongkheng/brokerage
Author: Goh Yong Kheng
Author-email: Goh Yong Kheng <goh.yongkheng@gmail.com>
License: MIT
Project-URL: Homepage, https://github.com/yongkheng/brokerage
Project-URL: Bug Tracker, https://github.com/yongkheng/brokerage/issues
Keywords: finance
Classifier: Programming Language :: Python :: 3
Classifier: License :: OSI Approved :: MIT License
Classifier: Operating System :: OS Independent
Requires-Python: >=3.7
License-File: LICENSE
